[
  {
    "id": 0,
    "question": "Apa ibu kota Indonesia?",
    "options": [
      { "text": "Jakarta", "value": 10 },
      { "text": "Bandung", "value": 0 },
      { "text": "Surabaya", "value": 0 },
      { "text": "Medan", "value": 0 }
    ],
    "durations": 10
  },
  {
    "id": 1,
    "question": "Siapa pencipta teori relativitas?",
    "options": [
      { "text": "Newton", "value": 0 },
      { "text": "Einstein", "value": 10 },
      { "text": "Galileo", "value": 0 },
      { "text": "Tesla", "value": 0 }
    ],
    "durations": 10
  }
]
